bounter_cmsc.pyd
bounter_htc.pyd
bounter/__init__.py
bounter/bounter.py
bounter/count_min_sketch.py
bounter/tests/__init__.py
bounter/tests/test_bounter.py
bounter/tests/cms/__init__.py
bounter/tests/cms/test_cms_basic.py
bounter/tests/cms/test_cms_init.py
bounter/tests/cms/test_cms_pickle.py
bounter/tests/cms/test_cms_quality.py
bounter/tests/cms/test_cms_statistical.py
bounter/tests/cms/test_cms_update.py
bounter/tests/hashtable/__init__.py
bounter/tests/hashtable/test_htc_get_set.py
bounter/tests/hashtable/test_htc_increment.py
bounter/tests/hashtable/test_htc_init.py
bounter/tests/hashtable/test_htc_iter_type.py
bounter/tests/hashtable/test_htc_iteration.py
bounter/tests/hashtable/test_htc_length.py
bounter/tests/hashtable/test_htc_pickle.py
bounter/tests/hashtable/test_htc_pruning.py
bounter/tests/hashtable/test_htc_quality.py
bounter/tests/hashtable/test_htc_total.py
bounter/tests/hashtable/test_htc_update.py
bounter-1.0.1.data/headers/hll.h
bounter-1.0.1.data/headers/murmur3.h
bounter-1.0.1.dist-info/DESCRIPTION.rst
bounter-1.0.1.dist-info/METADATA
bounter-1.0.1.dist-info/RECORD
bounter-1.0.1.dist-info/WHEEL
bounter-1.0.1.dist-info/metadata.json
bounter-1.0.1.dist-info/top_level.txt
